Metadata-Version: 2.4
Name: PySide6Plot
Version: 0.0.3
Summary: Scientific/Financial plot utilities with PySide6+pyqtgraph.
Author-email: YQ Cui <qianyun210603@hotmail.com>
License-Expression: MIT
Keywords: visualization,plotting,pyside6,pyqtgraph,financial,scientific
Classifier: Development Status :: 2 - Pre-Alpha
Classifier: Operating System :: POSIX :: Linux
Classifier: Operating System :: Microsoft :: Windows
Classifier: Programming Language :: Python :: 3
Classifier: Programming Language :: Python :: 3.11
Classifier: Programming Language :: Python :: 3.12
Classifier: Topic :: Scientific/Engineering :: Visualization
Classifier: Programming Language :: Python :: Implementation :: CPython
Requires-Python: >=3.11
Requires-Dist: numpy
Requires-Dist: pandas
Requires-Dist: pyaml>=23.10.0
Requires-Dist: PySide6!=6.9.1,>=6.9.0; python_version >= "3.12"
Requires-Dist: PySide6>=6.9.0; python_version <= "3.12"
Requires-Dist: pyqtgraph>=0.13.3
Requires-Dist: PySide6-Fluent-Widgets[full]>=1.5.1
Provides-Extra: dev
Requires-Dist: ruff>=0.0.263; extra == "dev"
Requires-Dist: setuptools_scm>=8; extra == "dev"
Requires-Dist: setuptools>=64; extra == "dev"
Requires-Dist: wheel; extra == "dev"
